hideme/__init__.py
hideme/proxy_collector.py
hideme/user_agents.txt
hideme-0.0.2.dist-info/LICENSE
hideme-0.0.2.dist-info/METADATA
hideme-0.0.2.dist-info/WHEEL
hideme-0.0.2.dist-info/top_level.txt
hideme-0.0.2.dist-info/RECORD
