Metadata-Version: 2.1
Name: hideme
Version: 0.0.2
Summary: A Python package to fetch usable proxies from the internet
Home-page: https://github.com/eckarthik/HideMe
Author: Karthik E C
Author-email: eckarthik39@gmail.com
License: UNKNOWN
Platform: UNKNOWN
Classifier: Programming Language :: Python :: 3
Classifier: License :: OSI Approved :: MIT License
Classifier: Operating System :: OS Independent
Requires-Python: >=3.0
